{
    "uid": "3cd81db0-1477-4264-a289-936ee0a32fce",
    "name": "9_Xgboost",
    "preprocessing": [
        {
            "ml_task": "binary_classification",
            "params": {
                "columns_preprocessing": {},
                "target_preprocessing": [
                    "na_exclude"
                ],
                "ml_task": "binary_classification"
            }
        },
        {
            "ml_task": "binary_classification",
            "params": {
                "columns_preprocessing": {},
                "target_preprocessing": [
                    "na_exclude"
                ],
                "ml_task": "binary_classification"
            }
        },
        {
            "ml_task": "binary_classification",
            "params": {
                "columns_preprocessing": {},
                "target_preprocessing": [
                    "na_exclude"
                ],
                "ml_task": "binary_classification"
            }
        },
        {
            "ml_task": "binary_classification",
            "params": {
                "columns_preprocessing": {},
                "target_preprocessing": [
                    "na_exclude"
                ],
                "ml_task": "binary_classification"
            }
        },
        {
            "ml_task": "binary_classification",
            "params": {
                "columns_preprocessing": {},
                "target_preprocessing": [
                    "na_exclude"
                ],
                "ml_task": "binary_classification"
            }
        }
    ],
    "learners": [
        {
            "library_version": "1.3.3",
            "algorithm_name": "Extreme Gradient Boosting",
            "algorithm_short_name": "Xgboost",
            "uid": "b7435c53-7a87-41a2-9105-4510b846fb2d",
            "params": {
                "model_type": "Xgboost",
                "ml_task": "binary_classification",
                "n_jobs": -1,
                "seed": 1236,
                "objective": "binary:logistic",
                "eta": 0.1,
                "max_depth": 8,
                "min_child_weight": 1,
                "subsample": 1.0,
                "colsample_bytree": 1.0,
                "eval_metric": "logloss",
                "explain_level": 2
            },
            "name": "learner_fold_0",
            "best_ntree_limit": 32
        },
        {
            "library_version": "1.3.3",
            "algorithm_name": "Extreme Gradient Boosting",
            "algorithm_short_name": "Xgboost",
            "uid": "58dd172c-0af2-4841-8c20-0fe08730e681",
            "params": {
                "model_type": "Xgboost",
                "ml_task": "binary_classification",
                "n_jobs": -1,
                "seed": 1236,
                "objective": "binary:logistic",
                "eta": 0.1,
                "max_depth": 8,
                "min_child_weight": 1,
                "subsample": 1.0,
                "colsample_bytree": 1.0,
                "eval_metric": "logloss",
                "explain_level": 2
            },
            "name": "learner_fold_1",
            "best_ntree_limit": 143
        },
        {
            "library_version": "1.3.3",
            "algorithm_name": "Extreme Gradient Boosting",
            "algorithm_short_name": "Xgboost",
            "uid": "4f0603ae-8016-4036-b72c-80e7186f348e",
            "params": {
                "model_type": "Xgboost",
                "ml_task": "binary_classification",
                "n_jobs": -1,
                "seed": 1236,
                "objective": "binary:logistic",
                "eta": 0.1,
                "max_depth": 8,
                "min_child_weight": 1,
                "subsample": 1.0,
                "colsample_bytree": 1.0,
                "eval_metric": "logloss",
                "explain_level": 2
            },
            "name": "learner_fold_2",
            "best_ntree_limit": 117
        },
        {
            "library_version": "1.3.3",
            "algorithm_name": "Extreme Gradient Boosting",
            "algorithm_short_name": "Xgboost",
            "uid": "ca139ca1-8e63-4f8e-94d6-afaccae3f617",
            "params": {
                "model_type": "Xgboost",
                "ml_task": "binary_classification",
                "n_jobs": -1,
                "seed": 1236,
                "objective": "binary:logistic",
                "eta": 0.1,
                "max_depth": 8,
                "min_child_weight": 1,
                "subsample": 1.0,
                "colsample_bytree": 1.0,
                "eval_metric": "logloss",
                "explain_level": 2
            },
            "name": "learner_fold_3",
            "best_ntree_limit": 38
        },
        {
            "library_version": "1.3.3",
            "algorithm_name": "Extreme Gradient Boosting",
            "algorithm_short_name": "Xgboost",
            "uid": "d84e06f8-cbb4-41c4-90af-b456f7fb5766",
            "params": {
                "model_type": "Xgboost",
                "ml_task": "binary_classification",
                "n_jobs": -1,
                "seed": 1236,
                "objective": "binary:logistic",
                "eta": 0.1,
                "max_depth": 8,
                "min_child_weight": 1,
                "subsample": 1.0,
                "colsample_bytree": 1.0,
                "eval_metric": "logloss",
                "explain_level": 2
            },
            "name": "learner_fold_4",
            "best_ntree_limit": 183
        }
    ],
    "params": {
        "additional": {
            "max_rounds": 10000,
            "early_stopping_rounds": 50,
            "max_rows_limit": null,
            "max_cols_limit": null
        },
        "preprocessing": {
            "columns_preprocessing": {},
            "target_preprocessing": [
                "na_exclude"
            ],
            "ml_task": "binary_classification"
        },
        "validation_strategy": {
            "validation_type": "kfold",
            "k_folds": 5,
            "shuffle": true,
            "stratify": true,
            "random_seed": 1230,
            "X_path": "AutoML_1/X.parquet",
            "y_path": "AutoML_1/y.parquet",
            "results_path": "AutoML_1"
        },
        "learner": {
            "model_type": "Xgboost",
            "ml_task": "binary_classification",
            "n_jobs": -1,
            "seed": 1236,
            "objective": "binary:logistic",
            "eta": 0.1,
            "max_depth": 8,
            "min_child_weight": 1,
            "subsample": 1.0,
            "colsample_bytree": 1.0,
            "eval_metric": "logloss",
            "explain_level": 2
        },
        "automl_random_state": 1234,
        "ml_task": "binary_classification",
        "explain_level": 2,
        "name": "9_Xgboost",
        "status": "initialized",
        "final_loss": null,
        "train_time": null,
        "data_type": "original",
        "max_time_for_learner": 200.0
    },
    "saved": [
        "9_Xgboost/learner_fold_0.xgboost",
        "9_Xgboost/learner_fold_1.xgboost",
        "9_Xgboost/learner_fold_2.xgboost",
        "9_Xgboost/learner_fold_3.xgboost",
        "9_Xgboost/learner_fold_4.xgboost"
    ],
    "predictions_fname": "9_Xgboost/predictions_out_of_folds.csv",
    "metric_name": "logloss",
    "final_loss": 0.1070581292274341,
    "train_time": 29.46849250793457,
    "is_stacked": false,
    "threshold": 0.5367600917816162
}