{
    "uid": "c448ac95-90b3-4e7f-a5e8-dc100f6c607d",
    "name": "22_RandomForest",
    "preprocessing": [
        {
            "categorical_y": {
                "B": 0,
                "M": 1
            },
            "ml_task": "binary_classification",
            "params": {
                "columns_preprocessing": {},
                "target_preprocessing": [
                    "na_exclude",
                    "categorical_to_int"
                ],
                "ml_task": "binary_classification"
            }
        },
        {
            "categorical_y": {
                "B": 0,
                "M": 1
            },
            "ml_task": "binary_classification",
            "params": {
                "columns_preprocessing": {},
                "target_preprocessing": [
                    "na_exclude",
                    "categorical_to_int"
                ],
                "ml_task": "binary_classification"
            }
        },
        {
            "categorical_y": {
                "B": 0,
                "M": 1
            },
            "ml_task": "binary_classification",
            "params": {
                "columns_preprocessing": {},
                "target_preprocessing": [
                    "na_exclude",
                    "categorical_to_int"
                ],
                "ml_task": "binary_classification"
            }
        },
        {
            "categorical_y": {
                "B": 0,
                "M": 1
            },
            "ml_task": "binary_classification",
            "params": {
                "columns_preprocessing": {},
                "target_preprocessing": [
                    "na_exclude",
                    "categorical_to_int"
                ],
                "ml_task": "binary_classification"
            }
        },
        {
            "categorical_y": {
                "B": 0,
                "M": 1
            },
            "ml_task": "binary_classification",
            "params": {
                "columns_preprocessing": {},
                "target_preprocessing": [
                    "na_exclude",
                    "categorical_to_int"
                ],
                "ml_task": "binary_classification"
            }
        }
    ],
    "learners": [
        {
            "library_version": "0.24.1",
            "algorithm_name": "Random Forest",
            "algorithm_short_name": "Random Forest",
            "uid": "de2a6935-7556-4e54-940f-c7d14a09e062",
            "params": {
                "model_type": "Random Forest",
                "ml_task": "binary_classification",
                "n_jobs": -1,
                "seed": 1238,
                "criterion": "entropy",
                "max_features": 0.6,
                "min_samples_split": 50,
                "max_depth": 6,
                "eval_metric_name": "logloss",
                "explain_level": 2
            },
            "name": "learner_fold_0"
        },
        {
            "library_version": "0.24.1",
            "algorithm_name": "Random Forest",
            "algorithm_short_name": "Random Forest",
            "uid": "604d5681-9a30-4683-afd4-255d19ca26c5",
            "params": {
                "model_type": "Random Forest",
                "ml_task": "binary_classification",
                "n_jobs": -1,
                "seed": 1238,
                "criterion": "entropy",
                "max_features": 0.6,
                "min_samples_split": 50,
                "max_depth": 6,
                "eval_metric_name": "logloss",
                "explain_level": 2
            },
            "name": "learner_fold_1"
        },
        {
            "library_version": "0.24.1",
            "algorithm_name": "Random Forest",
            "algorithm_short_name": "Random Forest",
            "uid": "80e5525c-757f-4ef7-be17-61823159fcfd",
            "params": {
                "model_type": "Random Forest",
                "ml_task": "binary_classification",
                "n_jobs": -1,
                "seed": 1238,
                "criterion": "entropy",
                "max_features": 0.6,
                "min_samples_split": 50,
                "max_depth": 6,
                "eval_metric_name": "logloss",
                "explain_level": 2
            },
            "name": "learner_fold_2"
        },
        {
            "library_version": "0.24.1",
            "algorithm_name": "Random Forest",
            "algorithm_short_name": "Random Forest",
            "uid": "ba6985af-9f74-4e72-b634-c1a5e7aa8220",
            "params": {
                "model_type": "Random Forest",
                "ml_task": "binary_classification",
                "n_jobs": -1,
                "seed": 1238,
                "criterion": "entropy",
                "max_features": 0.6,
                "min_samples_split": 50,
                "max_depth": 6,
                "eval_metric_name": "logloss",
                "explain_level": 2
            },
            "name": "learner_fold_3"
        },
        {
            "library_version": "0.24.1",
            "algorithm_name": "Random Forest",
            "algorithm_short_name": "Random Forest",
            "uid": "609b44a3-2aab-46db-a886-0a33608044f4",
            "params": {
                "model_type": "Random Forest",
                "ml_task": "binary_classification",
                "n_jobs": -1,
                "seed": 1238,
                "criterion": "entropy",
                "max_features": 0.6,
                "min_samples_split": 50,
                "max_depth": 6,
                "eval_metric_name": "logloss",
                "explain_level": 2
            },
            "name": "learner_fold_4"
        }
    ],
    "params": {
        "additional": {
            "trees_in_step": 100,
            "train_cant_improve_limit": 1,
            "min_steps": 1,
            "max_steps": 50,
            "early_stopping_rounds": 50,
            "max_rows_limit": null,
            "max_cols_limit": null
        },
        "preprocessing": {
            "columns_preprocessing": {},
            "target_preprocessing": [
                "na_exclude",
                "categorical_to_int"
            ],
            "ml_task": "binary_classification"
        },
        "validation_strategy": {
            "validation_type": "kfold",
            "k_folds": 5,
            "shuffle": true,
            "stratify": true,
            "random_seed": 1230,
            "X_path": "AutoML_1/X.parquet",
            "y_path": "AutoML_1/y.parquet",
            "results_path": "AutoML_1"
        },
        "learner": {
            "model_type": "Random Forest",
            "ml_task": "binary_classification",
            "n_jobs": -1,
            "seed": 1238,
            "criterion": "entropy",
            "max_features": 0.6,
            "min_samples_split": 50,
            "max_depth": 6,
            "eval_metric_name": "logloss",
            "explain_level": 2
        },
        "automl_random_state": 1234,
        "ml_task": "binary_classification",
        "explain_level": 2,
        "name": "22_RandomForest",
        "status": "initialized",
        "final_loss": null,
        "train_time": null,
        "data_type": "original",
        "max_time_for_learner": 200.0
    },
    "saved": [
        "22_RandomForest/learner_fold_0.random_forest",
        "22_RandomForest/learner_fold_1.random_forest",
        "22_RandomForest/learner_fold_2.random_forest",
        "22_RandomForest/learner_fold_3.random_forest",
        "22_RandomForest/learner_fold_4.random_forest"
    ],
    "predictions_fname": "22_RandomForest/predictions_out_of_folds.csv",
    "metric_name": "logloss",
    "final_loss": 0.1642002581996177,
    "train_time": 64.02077531814575,
    "is_stacked": false,
    "threshold": 0.4581975181563447
}