{
    "uid": "679b946f-0b25-4988-b123-d725d1388215",
    "name": "31_Xgboost_SelectedFeatures",
    "preprocessing": [
        {
            "categorical_y": {
                "B": 0,
                "M": 1
            },
            "ml_task": "binary_classification",
            "drop_features": [
                "radius_worst",
                "area_mean",
                "texture_se",
                "concavity_se",
                "radius_mean",
                "perimeter_se",
                "smoothness_se",
                "concavity_mean",
                "symmetry_mean",
                "concave points_se"
            ],
            "params": {
                "columns_preprocessing": {},
                "target_preprocessing": [
                    "na_exclude",
                    "categorical_to_int"
                ],
                "ml_task": "binary_classification",
                "drop_features": [
                    "radius_worst",
                    "area_mean",
                    "texture_se",
                    "concavity_se",
                    "radius_mean",
                    "perimeter_se",
                    "smoothness_se",
                    "concavity_mean",
                    "symmetry_mean",
                    "concave points_se",
                    "random_feature"
                ]
            }
        },
        {
            "categorical_y": {
                "B": 0,
                "M": 1
            },
            "ml_task": "binary_classification",
            "drop_features": [
                "radius_worst",
                "area_mean",
                "texture_se",
                "concavity_se",
                "radius_mean",
                "perimeter_se",
                "smoothness_se",
                "concavity_mean",
                "symmetry_mean",
                "concave points_se"
            ],
            "params": {
                "columns_preprocessing": {},
                "target_preprocessing": [
                    "na_exclude",
                    "categorical_to_int"
                ],
                "ml_task": "binary_classification",
                "drop_features": [
                    "radius_worst",
                    "area_mean",
                    "texture_se",
                    "concavity_se",
                    "radius_mean",
                    "perimeter_se",
                    "smoothness_se",
                    "concavity_mean",
                    "symmetry_mean",
                    "concave points_se",
                    "random_feature"
                ]
            }
        },
        {
            "categorical_y": {
                "B": 0,
                "M": 1
            },
            "ml_task": "binary_classification",
            "drop_features": [
                "radius_worst",
                "area_mean",
                "texture_se",
                "concavity_se",
                "radius_mean",
                "perimeter_se",
                "smoothness_se",
                "concavity_mean",
                "symmetry_mean",
                "concave points_se"
            ],
            "params": {
                "columns_preprocessing": {},
                "target_preprocessing": [
                    "na_exclude",
                    "categorical_to_int"
                ],
                "ml_task": "binary_classification",
                "drop_features": [
                    "radius_worst",
                    "area_mean",
                    "texture_se",
                    "concavity_se",
                    "radius_mean",
                    "perimeter_se",
                    "smoothness_se",
                    "concavity_mean",
                    "symmetry_mean",
                    "concave points_se",
                    "random_feature"
                ]
            }
        },
        {
            "categorical_y": {
                "B": 0,
                "M": 1
            },
            "ml_task": "binary_classification",
            "drop_features": [
                "radius_worst",
                "area_mean",
                "texture_se",
                "concavity_se",
                "radius_mean",
                "perimeter_se",
                "smoothness_se",
                "concavity_mean",
                "symmetry_mean",
                "concave points_se"
            ],
            "params": {
                "columns_preprocessing": {},
                "target_preprocessing": [
                    "na_exclude",
                    "categorical_to_int"
                ],
                "ml_task": "binary_classification",
                "drop_features": [
                    "radius_worst",
                    "area_mean",
                    "texture_se",
                    "concavity_se",
                    "radius_mean",
                    "perimeter_se",
                    "smoothness_se",
                    "concavity_mean",
                    "symmetry_mean",
                    "concave points_se",
                    "random_feature"
                ]
            }
        },
        {
            "categorical_y": {
                "B": 0,
                "M": 1
            },
            "ml_task": "binary_classification",
            "drop_features": [
                "radius_worst",
                "area_mean",
                "texture_se",
                "concavity_se",
                "radius_mean",
                "perimeter_se",
                "smoothness_se",
                "concavity_mean",
                "symmetry_mean",
                "concave points_se"
            ],
            "params": {
                "columns_preprocessing": {},
                "target_preprocessing": [
                    "na_exclude",
                    "categorical_to_int"
                ],
                "ml_task": "binary_classification",
                "drop_features": [
                    "radius_worst",
                    "area_mean",
                    "texture_se",
                    "concavity_se",
                    "radius_mean",
                    "perimeter_se",
                    "smoothness_se",
                    "concavity_mean",
                    "symmetry_mean",
                    "concave points_se",
                    "random_feature"
                ]
            }
        }
    ],
    "learners": [
        {
            "library_version": "1.3.3",
            "algorithm_name": "Extreme Gradient Boosting",
            "algorithm_short_name": "Xgboost",
            "uid": "8af29303-113b-4545-a071-ec35005b566f",
            "params": {
                "model_type": "Xgboost",
                "ml_task": "binary_classification",
                "n_jobs": -1,
                "objective": "binary:logistic",
                "eta": 0.05,
                "max_depth": 6,
                "min_child_weight": 1,
                "subsample": 1.0,
                "colsample_bytree": 1.0,
                "seed": 3,
                "eval_metric": "logloss",
                "explain_level": 2
            },
            "name": "learner_fold_0",
            "best_ntree_limit": 248
        },
        {
            "library_version": "1.3.3",
            "algorithm_name": "Extreme Gradient Boosting",
            "algorithm_short_name": "Xgboost",
            "uid": "a2d88b7e-a034-4153-ba98-040888463421",
            "params": {
                "model_type": "Xgboost",
                "ml_task": "binary_classification",
                "n_jobs": -1,
                "objective": "binary:logistic",
                "eta": 0.05,
                "max_depth": 6,
                "min_child_weight": 1,
                "subsample": 1.0,
                "colsample_bytree": 1.0,
                "seed": 3,
                "eval_metric": "logloss",
                "explain_level": 2
            },
            "name": "learner_fold_1",
            "best_ntree_limit": 251
        },
        {
            "library_version": "1.3.3",
            "algorithm_name": "Extreme Gradient Boosting",
            "algorithm_short_name": "Xgboost",
            "uid": "5b779c55-908d-4b40-91db-5abce9c0953b",
            "params": {
                "model_type": "Xgboost",
                "ml_task": "binary_classification",
                "n_jobs": -1,
                "objective": "binary:logistic",
                "eta": 0.05,
                "max_depth": 6,
                "min_child_weight": 1,
                "subsample": 1.0,
                "colsample_bytree": 1.0,
                "seed": 3,
                "eval_metric": "logloss",
                "explain_level": 2
            },
            "name": "learner_fold_2",
            "best_ntree_limit": 280
        },
        {
            "library_version": "1.3.3",
            "algorithm_name": "Extreme Gradient Boosting",
            "algorithm_short_name": "Xgboost",
            "uid": "e8ded141-b2c2-4382-bb30-59f0ff8cb019",
            "params": {
                "model_type": "Xgboost",
                "ml_task": "binary_classification",
                "n_jobs": -1,
                "objective": "binary:logistic",
                "eta": 0.05,
                "max_depth": 6,
                "min_child_weight": 1,
                "subsample": 1.0,
                "colsample_bytree": 1.0,
                "seed": 3,
                "eval_metric": "logloss",
                "explain_level": 2
            },
            "name": "learner_fold_3",
            "best_ntree_limit": 150
        },
        {
            "library_version": "1.3.3",
            "algorithm_name": "Extreme Gradient Boosting",
            "algorithm_short_name": "Xgboost",
            "uid": "fe6eea1c-5fa4-43fb-83d0-bdf5071260e9",
            "params": {
                "model_type": "Xgboost",
                "ml_task": "binary_classification",
                "n_jobs": -1,
                "objective": "binary:logistic",
                "eta": 0.05,
                "max_depth": 6,
                "min_child_weight": 1,
                "subsample": 1.0,
                "colsample_bytree": 1.0,
                "seed": 3,
                "eval_metric": "logloss",
                "explain_level": 2
            },
            "name": "learner_fold_4",
            "best_ntree_limit": 269
        }
    ],
    "params": {
        "additional": {
            "max_rounds": 10000,
            "early_stopping_rounds": 50,
            "max_rows_limit": null,
            "max_cols_limit": null
        },
        "preprocessing": {
            "columns_preprocessing": {},
            "target_preprocessing": [
                "na_exclude",
                "categorical_to_int"
            ],
            "ml_task": "binary_classification",
            "drop_features": [
                "radius_worst",
                "area_mean",
                "texture_se",
                "concavity_se",
                "radius_mean",
                "perimeter_se",
                "smoothness_se",
                "concavity_mean",
                "symmetry_mean",
                "concave points_se",
                "random_feature"
            ]
        },
        "validation_strategy": {
            "validation_type": "kfold",
            "k_folds": 5,
            "shuffle": true,
            "stratify": true,
            "random_seed": 1230,
            "X_path": "AutoML_1/X.parquet",
            "y_path": "AutoML_1/y.parquet",
            "results_path": "AutoML_1"
        },
        "learner": {
            "model_type": "Xgboost",
            "ml_task": "binary_classification",
            "n_jobs": -1,
            "objective": "binary:logistic",
            "eta": 0.05,
            "max_depth": 6,
            "min_child_weight": 1,
            "subsample": 1.0,
            "colsample_bytree": 1.0,
            "seed": 3,
            "eval_metric": "logloss",
            "explain_level": 2
        },
        "automl_random_state": 1234,
        "ml_task": "binary_classification",
        "explain_level": 2,
        "name": "31_Xgboost_SelectedFeatures",
        "status": "initialized",
        "final_loss": null,
        "train_time": null,
        "data_type": "original_features_selection",
        "max_time_for_learner": 200.0
    },
    "saved": [
        "31_Xgboost_SelectedFeatures/learner_fold_0.xgboost",
        "31_Xgboost_SelectedFeatures/learner_fold_1.xgboost",
        "31_Xgboost_SelectedFeatures/learner_fold_2.xgboost",
        "31_Xgboost_SelectedFeatures/learner_fold_3.xgboost",
        "31_Xgboost_SelectedFeatures/learner_fold_4.xgboost"
    ],
    "predictions_fname": "31_Xgboost_SelectedFeatures/predictions_out_of_folds.csv",
    "metric_name": "logloss",
    "final_loss": 0.11318086190088784,
    "train_time": 27.066489696502686,
    "is_stacked": false,
    "threshold": 0.5970713496208191
}